{
  "fileName": "story.tsx",
  "filePath": "components/linklist/story.tsx",
  "url": "https://github.com/technologiestiftung/kulturdaten-frontend/blob/master/components/linklist/story.tsx",
  "summary": "The code above is a React component that renders a list of links. It uses the `useLinkList` hook to generate the list of links based on the parameters passed to it. The component is also used as a story in Storybook, a tool for building UI components in isolation.\n\nThe `useLinkList` hook takes an object with the following properties:\n\n- `links`: an array of URLs to be displayed as links\n- `label`: a string that describes the list of links\n- `onChange`: a callback function that is called whenever the list of links is changed\n- `maxLinks`: an optional number that specifies the maximum number of links that can be displayed\n\nThe `useCallback` hook is used to memoize the `onChange` function so that it is only recreated when the `links` array changes. This can help improve performance by preventing unnecessary re-renders.\n\nThe `renderedLinkList` property returned by `useLinkList` is an array of React elements that represent the links. These elements are then rendered by the `X` component using the `{renderedLinkList}` syntax.\n\nThe `LinkListDefaultStory` is a Storybook story that renders the `X` component. This allows developers to preview the component in isolation and test its functionality.\n\nOverall, this code provides a reusable component for rendering lists of links with customizable labels and maximum link counts. It also demonstrates the use of Storybook for building and testing UI components.",
  "questions": "1. What is the purpose of the `useLinkList` hook being imported?\n   - The `useLinkList` hook is being used to render a list of links with a label and a maximum number of links, and to provide a callback function for when the links are changed.\n2. What is the significance of the `X` component?\n   - The `X` component is the main component being rendered, and it utilizes the `useLinkList` hook to generate a list of links with the specified properties.\n3. What is the purpose of the `LinkListDefaultStory` export?\n   - The `LinkListDefaultStory` export is a Storybook story that renders the `X` component, allowing developers to preview and test the link list component in isolation."
}